Metadata-Version: 2.1
Name: kmthachner
Version: 1.0.3
Summary: An NER API trained on CONLL2003
Author: Nguyen Kim Thach
Author-email: <kmthach.ai@gmail.com>
License-File: LICENSE
Requires-Dist: torch
Requires-Dist: seqeval
Requires-Dist: datasets
Requires-Dist: fastapi
Requires-Dist: uvicorn
